ucbox_plugin/__init__.py
ucbox_plugin/admin.py
ucbox_plugin/filters.py
ucbox_plugin/forms.py
ucbox_plugin/models.py
ucbox_plugin/navigation.py
ucbox_plugin/tables.py
ucbox_plugin/urls.py
ucbox_plugin/views.py
ucbox_plugin/api/__init__.py
ucbox_plugin/api/nested_serializers.py
ucbox_plugin/api/serializers.py
ucbox_plugin/api/urls.py
ucbox_plugin/api/views.py
ucbox_plugin/migrations/0001_initial.py
ucbox_plugin/migrations/__init__.py
ucbox_plugin/templates/ucbox_plugin/add_devicepool.html
ucbox_plugin/templates/ucbox_plugin/add_devicepool_3.x.html
ucbox_plugin/templates/ucbox_plugin/add_number.html
ucbox_plugin/templates/ucbox_plugin/add_number_3.x.html
ucbox_plugin/templates/ucbox_plugin/add_trunk.html
ucbox_plugin/templates/ucbox_plugin/add_trunk_3.x.html
ucbox_plugin/templates/ucbox_plugin/add_uccluster.html
ucbox_plugin/templates/ucbox_plugin/add_uccluster_3.x.html
ucbox_plugin/templates/ucbox_plugin/devicepool.html
ucbox_plugin/templates/ucbox_plugin/devicepool_3.x.html
ucbox_plugin/templates/ucbox_plugin/devicepool_list_view.html
ucbox_plugin/templates/ucbox_plugin/devicepool_list_view_3.x.html
ucbox_plugin/templates/ucbox_plugin/number.html
ucbox_plugin/templates/ucbox_plugin/number_3.x.html
ucbox_plugin/templates/ucbox_plugin/number_list_view.html
ucbox_plugin/templates/ucbox_plugin/number_list_view_3.x.html
ucbox_plugin/templates/ucbox_plugin/trunk.html
ucbox_plugin/templates/ucbox_plugin/trunk_3.x.html
ucbox_plugin/templates/ucbox_plugin/trunk_list_view.html
ucbox_plugin/templates/ucbox_plugin/trunk_list_view_3.x.html
ucbox_plugin/templates/ucbox_plugin/uccluster.html
ucbox_plugin/templates/ucbox_plugin/uccluster_3.x.html
ucbox_plugin/templates/ucbox_plugin/uccluster_list_view.html
ucbox_plugin/templates/ucbox_plugin/uccluster_list_view_3.x.html
ucbox_plugin-0.0.22.dist-info/LICENSE
ucbox_plugin-0.0.22.dist-info/METADATA
ucbox_plugin-0.0.22.dist-info/WHEEL
ucbox_plugin-0.0.22.dist-info/top_level.txt
ucbox_plugin-0.0.22.dist-info/RECORD
