Metadata-Version: 2.1
Name: ucbox-plugin
Version: 0.0.22
Summary: A unified communications management plugin for NetBox.
Home-page: https://github.com/levensailor/ucbox.git
Author: Jeff Levensailor
Author-email: jeff@levensailor.com
License: MIT
Keywords: netbox,netbox-plugin,plugin
Platform: UNKNOWN
Classifier: Development Status :: 4 - Beta
Classifier: Programming Language :: Python :: 3
Classifier: Programming Language :: Python :: 3.6
Classifier: Programming Language :: Python :: 3.7
Classifier: Programming Language :: Python :: 3.8
Classifier: Programming Language :: Python :: 3.9
License-File: LICENSE
